COPYING.txt
MANIFEST.in
README.txt
ez_setup.py
setup.py
bin/petri
bin/pyk-analyze
bin/pyk-compare
bin/pyk-comparison-graph
bin/pyk-mass-run
bin/pyk-profile
bin/pyk-publication-graph
bin/pyk-run
bin/pyk-test
docs/Makefile
docs/index.rst
docs/dev/building.rst
docs/dev/contents.rst
docs/dev/workflow.rst
docs/ref/conf.rst
docs/ref/data-format.rst
docs/ref/genome.rst
docs/ref/modules.rst
docs/ref/other_config_files.rst
docs/ref/petri.rst
docs/ref/sim/comp.rst
docs/ref/sim/env.rst
docs/ref/sim/fam.rst
docs/ref/sim/gen.rst
docs/ref/sim/org.rst
docs/ref/sim/sim.rst
docs/ref/test/test.rst
docs/ref/utils/analysis.rst
docs/ref/utils/comparison.rst
docs/ref/utils/globals.rst
docs/ref/utils/pics/ancestry.png
docs/ref/utils/pics/chemical_complexity.png
docs/ref/utils/pics/chemicals.png
docs/ref/utils/pics/comp_perc_func.png
docs/ref/utils/pics/complex_diversity.png
docs/ref/utils/pics/complexes.png
docs/ref/utils/pics/complexity.png
docs/ref/utils/pics/fam_length.png
docs/ref/utils/pics/fam_size.png
docs/ref/utils/pics/fitness.png
docs/ref/utils/pics/genome.png
docs/ref/utils/pics/invented_complexes.png
docs/ref/utils/pics/percent_functional.png
docs/ref/utils/pics/time_spent.png
docs/tut/deprecated.rst
docs/tut/installing.rst
docs/tut/intro.rst
docs/tut/petri.rst
docs/tut/running.rst
docs/tut/pics/10plot.png
docs/tut/pics/1plot.png
docs/tut/pics/analyze.png
docs/tut/pics/run.png
pykaryote/__init__.py
pykaryote.egg-info/PKG-INFO
pykaryote.egg-info/SOURCES.txt
pykaryote.egg-info/dependency_links.txt
pykaryote.egg-info/requires.txt
pykaryote.egg-info/top_level.txt
pykaryote/configs/cmp.cfg
pykaryote/configs/master.cfg
pykaryote/configs/sim.cfg
pykaryote/petri/__init__.py
pykaryote/petri/master.py
pykaryote/petri/tags.py
pykaryote/petri/worker.py
pykaryote/petri/config/petri_batch.cfg
pykaryote/petri/config/petri_settings.cfg
pykaryote/sim/__init__.py
pykaryote/sim/complexes.c
pykaryote/sim/complexes.pxd
pykaryote/sim/complexes.pyx
pykaryote/sim/environment.c
pykaryote/sim/environment.pyx
pykaryote/sim/families.c
pykaryote/sim/families.pyx
pykaryote/sim/genome.c
pykaryote/sim/genome.pyx
pykaryote/sim/organism.c
pykaryote/sim/organism.pyx
