Metadata-Version: 1.1
Name: pykaryote
Version: 1.1.1
Summary: Tools for modeling the evolution of biological complexity
Home-page: https://pykaryote.readthedocs.org/en/latest/
Author: James Lamine, Ethan Van Andel, Peter Vandehaar
Author-email: UNKNOWN
License: UNKNOWN
Platform: UNKNOWN
Classifier: Programming Language :: Python
Classifier: Programming Language :: Python :: 2
Classifier: Programming Language :: Python :: 2.7
Classifier: Programming Language :: Cython
Classifier: Development Status :: 4 - Beta
Classifier: Intended Audience :: Science/Research
Classifier: License :: OSI Approved :: GNU General Public License (GPL)
Classifier: Operating System :: OS Independent
Classifier: Topic :: Scientific/Engineering :: Artificial Life
Classifier: Topic :: Scientific/Engineering :: Physics
Provides: pykaryote
